cryptapi/__init__.py
cryptapi/admin.py
cryptapi/choices.py
cryptapi/config.py
cryptapi/dispatchers.py
cryptapi/forms.py
cryptapi/helpers.py
cryptapi/meta.py
cryptapi/models.py
cryptapi/settings.py
cryptapi/signals.py
cryptapi/urls.py
cryptapi/utils.py
cryptapi/views.py
cryptapi/__pycache__/__init__.cpython-36.pyc
cryptapi/__pycache__/__init__.cpython-37.pyc
cryptapi/__pycache__/admin.cpython-36.pyc
cryptapi/__pycache__/admin.cpython-37.pyc
cryptapi/__pycache__/choices.cpython-36.pyc
cryptapi/__pycache__/choices.cpython-37.pyc
cryptapi/__pycache__/config.cpython-36.pyc
cryptapi/__pycache__/config.cpython-37.pyc
cryptapi/__pycache__/dispatchers.cpython-36.pyc
cryptapi/__pycache__/dispatchers.cpython-37.pyc
cryptapi/__pycache__/forms.cpython-36.pyc
cryptapi/__pycache__/forms.cpython-37.pyc
cryptapi/__pycache__/helpers.cpython-36.pyc
cryptapi/__pycache__/helpers.cpython-37.pyc
cryptapi/__pycache__/meta.cpython-36.pyc
cryptapi/__pycache__/meta.cpython-37.pyc
cryptapi/__pycache__/models.cpython-36.pyc
cryptapi/__pycache__/models.cpython-37.pyc
cryptapi/__pycache__/settings.cpython-36.pyc
cryptapi/__pycache__/settings.cpython-37.pyc
cryptapi/__pycache__/urls.cpython-36.pyc
cryptapi/__pycache__/urls.cpython-37.pyc
cryptapi/__pycache__/utils.cpython-36.pyc
cryptapi/__pycache__/utils.cpython-37.pyc
cryptapi/__pycache__/views.cpython-36.pyc
cryptapi/__pycache__/views.cpython-37.pyc
cryptapi/migrations/0001_initial.py
cryptapi/migrations/0002_provider_last_updated.py
cryptapi/migrations/0003_auto_20181112_1939.py
cryptapi/migrations/0004_auto_20190729_1132.py
cryptapi/migrations/0005_auto_20200504_2323.py
cryptapi/migrations/0006_auto_20200505_0304.py
cryptapi/migrations/0007_auto_20200827_1510.py
cryptapi/migrations/__init__.py
cryptapi/migrations/__pycache__/0001_initial.cpython-36.pyc
cryptapi/migrations/__pycache__/0002_provider_last_updated.cpython-36.pyc
cryptapi/migrations/__pycache__/0003_auto_20181112_1939.cpython-36.pyc
django_cryptapi-0.3.1.dist-info/LICENSE
django_cryptapi-0.3.1.dist-info/METADATA
django_cryptapi-0.3.1.dist-info/PKG-INFO[Conflict]
django_cryptapi-0.3.1.dist-info/SOURCES[Conflict].txt
django_cryptapi-0.3.1.dist-info/WHEEL
django_cryptapi-0.3.1.dist-info/top_level.txt
django_cryptapi-0.3.1.dist-info/RECORD
