Metadata-Version: 2.1
Name: django-cryptapi
Version: 0.3.1
Summary: Django implementation of CryptAPI's payment gateway
Home-page: https://github.com/cryptapi/django-cryptapi
Author: CryptAPI
Author-email: cryptapi@protonmail.com
License: MIT
Platform: UNKNOWN
Classifier: Programming Language :: Python
Classifier: Development Status :: 4 - Beta
Classifier: Framework :: Django
Classifier: Intended Audience :: Developers
Classifier: License :: OSI Approved :: MIT License
Classifier: Natural Language :: English
Classifier: Operating System :: OS Independent
Classifier: Programming Language :: Python :: 3
Requires-Dist: django
Requires-Dist: requests
